README.rst
setup.cfg
setup.py
HiDi.egg-info/PKG-INFO
HiDi.egg-info/SOURCES.txt
HiDi.egg-info/dependency_links.txt
HiDi.egg-info/requires.txt
HiDi.egg-info/top_level.txt
hidi/__init__.py
hidi/clean.py
hidi/forking.py
hidi/inout.py
hidi/linalg.py
hidi/matrix.py
hidi/pipeline.py
hidi/transform.py
hidi/examples/__init__.py
hidi/examples/forking.py
hidi/examples/simple.py