Metadata-Version: 1.1
Name: HiDi
Version: 0.0.2
Summary: High-dimensional embedding generation library
Home-page: https://github.com/vevo/hidi
Author: Vevo Engineering
Author-email: engineering@vevo.com
License: ALv2
Platform: UNKNOWN
Classifier: Programming Language :: Python :: 2.7
Classifier: Programming Language :: Python :: 3.4
Classifier: Programming Language :: Python :: 3.5
Classifier: Programming Language :: Python :: 3.6
